safe_environ/__init__.py
safe_environ/environ.py
safe_environ/exceptions.py
safe_environ-0.1.0.dist-info/LICENSE.md
safe_environ-0.1.0.dist-info/METADATA
safe_environ-0.1.0.dist-info/WHEEL
safe_environ-0.1.0.dist-info/top_level.txt
safe_environ-0.1.0.dist-info/RECORD
